pyrobby-0.2.1.data/data/robot/answers.html
pyrobby-0.2.1.data/data/robot/icons/close_tab.png
pyrobby-0.2.1.data/data/robot/icons/end.png
pyrobby-0.2.1.data/data/robot/icons/new_tab.png
pyrobby-0.2.1.data/data/robot/icons/open.png
pyrobby-0.2.1.data/data/robot/icons/remote-control.png
pyrobby-0.2.1.data/data/robot/icons/reset.png
pyrobby-0.2.1.data/data/robot/icons/restore.png
pyrobby-0.2.1.data/data/robot/icons/return.png
pyrobby-0.2.1.data/data/robot/icons/robot.png
pyrobby-0.2.1.data/data/robot/icons/save.png
pyrobby-0.2.1.data/data/robot/icons/start.png
robot/__init__.py
robot/answers.html
robot/robot.py
robot/tasks.py
robot/icons/close_tab.png
robot/icons/end.png
robot/icons/new_tab.png
robot/icons/open.png
robot/icons/photo-env_window.png
robot/icons/photo-remote.png
robot/icons/photo-result_window.png
robot/icons/remote-control.png
robot/icons/reset.png
robot/icons/restore.png
robot/icons/return.png
robot/icons/robot.png
robot/icons/save.png
robot/icons/start.png
pyrobby-0.2.1.dist-info/LICENSE
pyrobby-0.2.1.dist-info/METADATA
pyrobby-0.2.1.dist-info/WHEEL
pyrobby-0.2.1.dist-info/top_level.txt
pyrobby-0.2.1.dist-info/RECORD
